syngen/VERSION
syngen/__init__.py
syngen/infer.py
syngen/sdk.py
syngen/train.py
syngen/__pycache__/__init__.cpython-311.pyc
syngen/__pycache__/infer.cpython-311.pyc
syngen/__pycache__/sdk.cpython-311.pyc
syngen/__pycache__/train.cpython-311.pyc
syngen/ml/__init__.py
syngen/ml/__pycache__/__init__.cpython-311.pyc
syngen/ml/config/__init__.py
syngen/ml/config/configurations.py
syngen/ml/config/validation.py
syngen/ml/config/__pycache__/__init__.cpython-311.pyc
syngen/ml/config/__pycache__/configurations.cpython-311.pyc
syngen/ml/config/__pycache__/validation.cpython-311.pyc
syngen/ml/context/__init__.py
syngen/ml/context/context.py
syngen/ml/context/__pycache__/__init__.cpython-311.pyc
syngen/ml/context/__pycache__/context.cpython-311.pyc
syngen/ml/convertor/__init__.py
syngen/ml/convertor/convertor.py
syngen/ml/convertor/__pycache__/__init__.cpython-311.pyc
syngen/ml/convertor/__pycache__/convertor.cpython-311.pyc
syngen/ml/data_loaders/__init__.py
syngen/ml/data_loaders/data_loaders.py
syngen/ml/data_loaders/dataframe_fetcher.py
syngen/ml/data_loaders/__pycache__/__init__.cpython-311.pyc
syngen/ml/data_loaders/__pycache__/data_loaders.cpython-311.pyc
syngen/ml/data_loaders/__pycache__/dataframe_fetcher.cpython-311.pyc
syngen/ml/flatten_json/__init__.py
syngen/ml/flatten_json/flatten_json.py
syngen/ml/flatten_json/__pycache__/__init__.cpython-311.pyc
syngen/ml/flatten_json/__pycache__/flatten_json.cpython-311.pyc
syngen/ml/handlers/__init__.py
syngen/ml/handlers/handlers.py
syngen/ml/handlers/__pycache__/__init__.cpython-311.pyc
syngen/ml/handlers/__pycache__/handlers.cpython-311.pyc
syngen/ml/metrics/.gitkeep
syngen/ml/metrics/__init__.py
syngen/ml/metrics/utils.py
syngen/ml/metrics/__pycache__/__init__.cpython-311.pyc
syngen/ml/metrics/__pycache__/utils.cpython-311.pyc
syngen/ml/metrics/accuracy_test/__init__.py
syngen/ml/metrics/accuracy_test/accuracy_report.html
syngen/ml/metrics/accuracy_test/accuracy_test.py
syngen_databricks-0.10.32.dist-info/licenses/LICENSE
syngen_databricks-0.10.32.dist-info/METADATA
syngen_databricks-0.10.32.dist-info/WHEEL
syngen_databricks-0.10.32.dist-info/entry_points.txt
syngen_databricks-0.10.32.dist-info/top_level.txt
syngen_databricks-0.10.32.dist-info/RECORD
